{"id":"180004","item":"Metalic Hole","url":"http:\/\/videohive.net\/item\/metalic-hole\/180004","user":"okanakdeniz","thumbnail":"https:\/\/0.s3.envato.com\/files\/1758139\/metalic%20hole%20thumb.jpg","sales":"3","rating":"0.0","rating_decimal":"0.00","cost":"4.00","uploaded_on":"Mon Mar 21 12:35:09 +1100 2011","last_update":"Mon Mar 21 12:35:09 +1100 2011","tags":"abstract background, black, bullet hole, business, corporate, dark, dimension, gray, intro, iron, logo, metalic, texture, zoom","category":"stock-footage\/technology","live_preview_url":"https:\/\/0.s3.envato.com\/files\/1758138\/Metalic%20hole%20preview.jpg","live_preview_video_url":"https:\/\/0.s3.envato.com\/files\/1758140\/Metalic%20Hole%20Preview.flv"}