{"id":"6169408","item":"Ripple Photo Album","url":"http:\/\/videohive.net\/item\/ripple-photo-album\/6169408","user":"orangeornate","thumbnail":"https:\/\/3.s3.envato.com\/files\/74107982\/Thumb.jpg","sales":"92","rating":"0.0","rating_decimal":"0.00","cost":"20.00","uploaded_on":"Tue Nov 26 06:06:13 +1100 2013","last_update":"Tue Nov 26 06:06:13 +1100 2013","tags":"artistic transition, asthetic, cinematic opener, dark, dramatic intro, drawing, film mattes, film opener, film reel, grunge, leak, light, ripple, slideshow, smooth","category":"after-effects-project-files\/video-displays\/grunge","live_preview_url":"https:\/\/1.s3.envato.com\/files\/74107998\/inline_display.jpg","live_preview_video_url":"https:\/\/3.s3.envato.com\/files\/74107997\/preview.flv"}