{"id":"1358572","item":"happy valentine's day calender","url":"http:\/\/videohive.net\/item\/happy-valentines-day-calender\/1358572","user":"sonderson","thumbnail":"https:\/\/2.s3.envato.com\/files\/15719486\/hvd_thumbs.jpg","sales":"11","rating":"0.0","rating_decimal":"0.00","cost":"4.00","uploaded_on":"Tue Jan 24 08:08:58 +1100 2012","last_update":"Tue Jan 24 08:08:58 +1100 2012","tags":"14 february, calender, happy, happy valentine's day, love, man, pink, women","category":"motion-graphics\/miscellaneous\/events","live_preview_url":"https:\/\/0.s3.envato.com\/files\/15719468\/hvd_pre.jpg","live_preview_video_url":"https:\/\/1.s3.envato.com\/files\/15719490\/valentines%20day.flv"}