{"id":"5586340","item":"222 Animated Icons","url":"http:\/\/videohive.net\/item\/222-animated-icons\/5586340","user":"risto","thumbnail":"https:\/\/0.s3.envato.com\/files\/100489464\/icons-thumbnail.jpg","sales":"1390","rating":"5.0","rating_decimal":"4.94","cost":"42.00","uploaded_on":"Wed Sep 18 21:10:44 +1000 2013","last_update":"Wed Aug 06 17:30:13 +1000 2014","tags":"corporate, flat, icon, icon set, internet, loop, minimalistic, money, pack, package, people, social, symbol, tablet, web","category":"after-effects-project-files\/elements\/miscellaneous\/corporate","live_preview_url":"https:\/\/0.s3.envato.com\/files\/100489476\/icons-preview.jpg","live_preview_video_url":"https:\/\/0.s3.envato.com\/files\/100489474\/Preview-vid.flv"}