{"id":"7845415","item":"Wood Construction Country House ","url":"http:\/\/videohive.net\/item\/wood-construction-country-house-\/7845415","user":"reshaemo","thumbnail":"https:\/\/2.s3.envato.com\/files\/92597719\/80x80_01015.jpg","sales":"0","rating":"0.0","rating_decimal":"0.00","cost":"5.00","uploaded_on":"Fri May 30 07:33:04 +1000 2014","last_update":"Fri May 30 07:33:04 +1000 2014","tags":"building a country house, construction, country house, framework, the foundation of house, wood construction","category":"stock-footage\/buildings","live_preview_url":"https:\/\/1.s3.envato.com\/files\/92597750\/590x300_00000.jpg","live_preview_video_url":"https:\/\/1.s3.envato.com\/files\/92597749\/Preview.flv"}