{"id":"6221593","item":"Office Girl Having an Anxiety Attack at Work","url":"http:\/\/videohive.net\/item\/office-girl-having-an-anxiety-attack-at-work\/6221593","user":"wriker36","thumbnail":"https:\/\/0.s3.envato.com\/files\/73925162\/office_girl-07.png","sales":"12","rating":"0.0","rating_decimal":"0.00","cost":"6.00","uploaded_on":"Thu Nov 28 14:56:36 +1100 2013","last_update":"Thu Nov 28 14:56:36 +1100 2013","tags":"alone, anxious, business, corporate, cubicle, frightened, medication, office, pressure, sad, sales, scared, stressed, unhappy","category":"stock-footage\/people","live_preview_url":"https:\/\/0.s3.envato.com\/files\/73925174\/office_girl-07.jpg","live_preview_video_url":"https:\/\/0.s3.envato.com\/files\/73925173\/office_girl-07.mp4"}