{"id":"2300102","item":"Beach, Wave and Seaweed II","url":"http:\/\/videohive.net\/item\/beach-wave-and-seaweed-ii\/2300102","user":"azamshah72v","thumbnail":"https:\/\/0.s3.envato.com\/files\/26594212\/BeachSeaweedWave8080.jpg","sales":"0","rating":"0.0","rating_decimal":"0.00","cost":"6.00","uploaded_on":"Mon May 07 09:01:03 +1000 2012","last_update":"Mon May 07 09:01:03 +1000 2012","tags":"beach, bubbles, malaysia, nature, picnic, recreation, sand, sandy, sea, seaweed, shore, tide. ocean, wave","category":"stock-footage\/nature","live_preview_url":"https:\/\/0.s3.envato.com\/files\/26594215\/BeachSeaweedWave590300.jpg","live_preview_video_url":"https:\/\/0.s3.envato.com\/files\/26594214\/BeachSeaweedWave6436.flv"}