{"id":"3113286","item":"Romantic Loopable Background","url":"http:\/\/videohive.net\/item\/romantic-loopable-background\/3113286","user":"masterdot","thumbnail":"https:\/\/0.s3.envato.com\/files\/35863062\/Romantic-Loopable%20Background-Thumb.jpg","sales":"3","rating":"0.0","rating_decimal":"0.00","cost":"6.00","uploaded_on":"Mon Oct 01 02:42:30 +1000 2012","last_update":"Mon Oct 01 02:42:30 +1000 2012","tags":"Events Television Backdrops, bachelors party, birthday party, ceremony, friendship day, loop able background, loopable love babble animation, love relationship, marriage, romance day, romantic, soft logo placeholder, title credits, valentine day, wedding celebration","category":"motion-graphics\/backgrounds\/miscellaneous","live_preview_url":"https:\/\/0.s3.envato.com\/files\/35863077\/Romantic-Loopable%20Background-Preview.jpg","live_preview_video_url":"https:\/\/0.s3.envato.com\/files\/35863074\/Romantic-Loopable%20Background-Preview.flv"}