{"id":"471160","item":"Stacks of $100 Bills Falling into a Pile + Alpha","url":"http:\/\/videohive.net\/item\/stacks-of-100-bills-falling-into-a-pile-alpha\/471160","user":"butlerm","thumbnail":"https:\/\/0.s3.envato.com\/files\/5240617\/80_100_bills.jpg","sales":"66","rating":"4.5","rating_decimal":"4.60","cost":"7.00","uploaded_on":"Sun Aug 14 12:07:43 +1000 2011","last_update":"Sun Aug 14 12:07:43 +1000 2011","tags":"bill, bills, cash, dollar, dollars, falling, group, heap, hundred, investment, money, pile of, stack, win","category":"motion-graphics\/elements\/corporate","live_preview_url":"https:\/\/0.s3.envato.com\/files\/5240616\/590_100_bills.jpg","live_preview_video_url":"https:\/\/0.s3.envato.com\/files\/5240618\/640_100_Bills.flv"}