{"id":"1925816","item":"Soccer Field Rotating","url":"http:\/\/videohive.net\/item\/soccer-field-rotating\/1925816","user":"cybersurge","thumbnail":"https:\/\/0.s3.envato.com\/files\/22309085\/Soccer%20Field%20Rotating%20.png","sales":"108","rating":"4.5","rating_decimal":"4.57","cost":"5.00","uploaded_on":"Tue Apr 03 03:48:34 +1000 2012","last_update":"Tue Apr 03 03:48:34 +1000 2012","tags":"arena, background, college, field, football, goal, grass, gridiron, loopable, soccer, sports","category":"motion-graphics\/backgrounds\/sports","live_preview_url":"https:\/\/0.s3.envato.com\/files\/22309088\/Soccer%20Field%20Rotating.jpg","live_preview_video_url":"https:\/\/0.s3.envato.com\/files\/22309087\/Soccer%20Field%20Rotating.flv"}