{"id":"166944","item":"Love story Wedding Album HD","url":"http:\/\/videohive.net\/item\/love-story-wedding-album-hd\/166944","user":"signs09","thumbnail":"https:\/\/0.s3.envato.com\/files\/1625030\/LoveStory%20Thumbnail80.jpg","sales":"50","rating":"5.0","rating_decimal":"4.89","cost":"32.00","uploaded_on":"Thu Mar 10 21:42:12 +1100 2011","last_update":"Thu Mar 10 21:42:12 +1100 2011","tags":"beige, blue, gold, life, love story, people, red, stories, weddings","category":"after-effects-project-files\/video-displays\/special-events","live_preview_url":"https:\/\/0.s3.envato.com\/files\/1625029\/LOveStory%20590X300.jpg","live_preview_video_url":"https:\/\/0.s3.envato.com\/files\/1625031\/WEDDINGS%20MEMORIES%20ALBUM%20PREVIEW.flv"}