{"id":"5792981","item":"Halloween Scary Cat","url":"http:\/\/videohive.net\/item\/halloween-scary-cat\/5792981","user":"FXBoxx","thumbnail":"https:\/\/2.s3.envato.com\/files\/69181364\/12_HalloweenScaryCat01_Thumb.jpg","sales":"5","rating":"0.0","rating_decimal":"0.00","cost":"5.00","uploaded_on":"Sat Oct 12 01:53:51 +1100 2013","last_update":"Sat Oct 12 01:53:51 +1100 2013","tags":"Harvest Festival, autumn season, broadcast bg, creepy cat, fright night, halloween, holidays, horror bungalow, retro promo, scary trees, spooky pumpkins, thanksgiving, trick or treat, web commercial","category":"motion-graphics\/backgrounds\/events","live_preview_url":"https:\/\/1.s3.envato.com\/files\/69181367\/12_HalloweenScaryCat01.jpg","live_preview_video_url":"https:\/\/2.s3.envato.com\/files\/69181366\/12_HalloweenScaryCat01.flv"}