{"id":"1838438","item":"Merry-Go-Round And Ferris Wheel 1","url":"http:\/\/videohive.net\/item\/merrygoround-and-ferris-wheel-1\/1838438","user":"spafron","thumbnail":"https:\/\/0.s3.envato.com\/files\/21318521\/Carnival%20Ferris%20Wheel%20Merry%20Go%20Round%20thumb.jpg","sales":"32","rating":"4.5","rating_decimal":"4.25","cost":"6.00","uploaded_on":"Fri Mar 16 15:59:36 +1100 2012","last_update":"Fri Mar 16 15:59:36 +1100 2012","tags":"amusement park, carnival, children, fair, family, festival, fun, kids","category":"stock-footage\/special-events","live_preview_url":"https:\/\/0.s3.envato.com\/files\/21318539\/Carnival%20Ferris%20Wheel%20Merry%20Go%20Round%20preview.jpg","live_preview_video_url":"https:\/\/0.s3.envato.com\/files\/21318535\/Carnival%20Ferris%20Wheel%20Merry%20Go%20Round.flv"}