{"id":"2894100","item":"3D Animation Background \/ Virtual Set","url":"http:\/\/videohive.net\/item\/3d-animation-background-virtual-set\/2894100","user":"alesul","thumbnail":"https:\/\/0.s3.envato.com\/files\/33303332\/thumbs.jpg","sales":"96","rating":"4.5","rating_decimal":"4.27","cost":"6.00","uploaded_on":"Tue Aug 28 00:11:15 +1000 2012","last_update":"Tue Aug 28 00:11:15 +1000 2012","tags":"3d, background, chapter, clean, environment, passage, presenter, scenary, set, video, vignette, virtual, wedding, white","category":"motion-graphics\/backgrounds\/3d-object","live_preview_url":"https:\/\/0.s3.envato.com\/files\/33303343\/preview_jpeg.jpg","live_preview_video_url":"https:\/\/0.s3.envato.com\/files\/33455085\/anim_preview.flv"}