{"id":"7848050","item":"Laptop Typing","url":"http:\/\/videohive.net\/item\/laptop-typing\/7848050","user":"creativesight","thumbnail":"https:\/\/0.s3.envato.com\/files\/4d689bbf-605e-4870-b193-e9d2d9892c8c\/thumbnail.jpeg","sales":"5","rating":"0.0","rating_decimal":"0.00","cost":"5.00","uploaded_on":"Fri May 30 11:11:30 +1000 2014","last_update":"Fri Jun 06 11:04:11 +1000 2014","tags":"backlit, business, businessman, click, clicking, computer, corporate, email, key, keyboard, laptop, letter, office, work, writer","category":"stock-footage\/business-corporate","live_preview_url":"https:\/\/0.s3.envato.com\/files\/4d689bbf-605e-4870-b193-e9d2d9892c8c\/inline_image_preview.jpeg","live_preview_video_url":"https:\/\/0.s3.envato.com\/files\/4d689bbf-605e-4870-b193-e9d2d9892c8c\/video_preview.mp4"}