{"id":"3750036","item":"Working With Laptop 3","url":"http:\/\/videohive.net\/item\/working-with-laptop-3\/3750036","user":"stockfactory","thumbnail":"https:\/\/2.s3.envato.com\/files\/55884076\/F%20Working%20With%20Laptop%203%20THUMBNAIL.jpg","sales":"24","rating":"4.5","rating_decimal":"4.67","cost":"6.00","uploaded_on":"Fri Jan 11 04:21:14 +1100 2013","last_update":"Fri Jan 11 04:21:14 +1100 2013","tags":"Working At Home, business, computer, computer monitor, desk, facebook, human hand, internet, laptop, men, office, typing, working","category":"stock-footage\/business-corporate","live_preview_url":"https:\/\/2.s3.envato.com\/files\/55884077\/F%20Working%20With%20Laptop%203%20PREVIEW%20IMAGE.jpg","live_preview_video_url":"https:\/\/0.s3.envato.com\/files\/44959922\/Working%20With%20Laptop%203%20PREVIEW.flv"}