{"id":"795602","item":"HD Slow Motion Red Ink Water Flow","url":"http:\/\/videohive.net\/item\/hd-slow-motion-red-ink-water-flow\/795602","user":"kwizsatzhaderach","thumbnail":"https:\/\/0.s3.envato.com\/files\/11651140\/red_small.jpg","sales":"28","rating":"4.5","rating_decimal":"4.60","cost":"21.00","uploaded_on":"Fri Nov 18 02:46:20 +1100 2011","last_update":"Fri Nov 18 02:46:20 +1100 2011","tags":"Ink Flow, black, cloud chamber, design element, drop, ink, paint, red, slow motion, smoke, water","category":"stock-footage\/slow-motion","live_preview_url":"https:\/\/0.s3.envato.com\/files\/11651136\/big_red.jpg","live_preview_video_url":"https:\/\/0.s3.envato.com\/files\/9191428\/INK_RED2x_111111.flv"}