{"id":"126362","item":"3D Monitor Machine","url":"http:\/\/videohive.net\/item\/3d-monitor-machine\/126362","user":"Manuelandro","thumbnail":"https:\/\/2.s3.envato.com\/files\/1172632\/miniature.jpg","sales":"73","rating":"4.5","rating_decimal":"4.53","cost":"25.00","uploaded_on":"Tue Sep 28 06:34:26 +1000 2010","last_update":"Tue Sep 28 06:34:26 +1000 2010","tags":"3d, animation, black, gray, green, machine, monitor, object, robot, white","category":"after-effects-project-files\/video-displays\/3d-object","live_preview_url":"https:\/\/3.s3.envato.com\/files\/1172631\/preview_image.jpg","live_preview_video_url":"https:\/\/0.s3.envato.com\/files\/1172633\/PREVIEW.flv"}