{"id":"1960208","item":"Smoked Sun 3","url":"http:\/\/videohive.net\/item\/smoked-sun-3\/1960208","user":"AndrVlad","thumbnail":"https:\/\/0.s3.envato.com\/files\/22711480\/smoked_sun3_80x80.jpg","sales":"27","rating":"0.0","rating_decimal":"0.00","cost":"7.00","uploaded_on":"Tue Mar 27 09:07:45 +1100 2012","last_update":"Tue Mar 27 09:07:45 +1100 2012","tags":"cinematic, clouds, hide, move, sky, smoke, sun","category":"stock-footage\/slow-motion","live_preview_url":"https:\/\/0.s3.envato.com\/files\/22711521\/smoked_sun3_590x300.jpg","live_preview_video_url":"https:\/\/0.s3.envato.com\/files\/22711518\/smoked_sun3_preview.flv"}