{"id":"5702822","item":"Hand Sign: The Symbol Of Victory","url":"http:\/\/videohive.net\/item\/hand-sign-the-symbol-of-victory\/5702822","user":"GoodMan_Ekim","thumbnail":"https:\/\/0.s3.envato.com\/files\/67909179\/victory_sign_thum.jpg","sales":"1","rating":"0.0","rating_decimal":"0.00","cost":"6.00","uploaded_on":"Tue Oct 01 23:33:46 +1000 2013","last_update":"Tue Oct 01 23:33:46 +1000 2013","tags":"achievement, arm sign, cheerful, fingers, freedom, gesture, hand, man, peace, positive, success, symbol, victory, win, winner","category":"stock-footage\/people","live_preview_url":"https:\/\/0.s3.envato.com\/files\/67909188\/victory_sign_prev.jpg","live_preview_video_url":"https:\/\/0.s3.envato.com\/files\/67909187\/victory_sign.flv"}