{"id":"5361095","item":"3D City 4","url":"http:\/\/videohive.net\/item\/3d-city-4\/5361095","user":"ColorfulUmbrella","thumbnail":"https:\/\/1.s3.envato.com\/files\/63815271\/Thumbnail_00100.jpg","sales":"0","rating":"0.0","rating_decimal":"0.00","cost":"4.00","uploaded_on":"Thu Aug 22 22:42:46 +1000 2013","last_update":"Thu Aug 22 22:42:46 +1000 2013","tags":"3d, 3d city, architecture, business, c4d, city, communication, element, global, internet, render, social, society, world","category":"motion-graphics\/backgrounds\/3d-object","live_preview_url":"https:\/\/3.s3.envato.com\/files\/63815274\/Preview%20Image_00089.jpg","live_preview_video_url":"https:\/\/2.s3.envato.com\/files\/64672640\/Video%20Preview.flv"}