{"id":"242422","item":"My New York","url":"http:\/\/videohive.net\/item\/my-new-york\/242422","user":"DaniMult","thumbnail":"https:\/\/0.s3.envato.com\/files\/4627930\/NY_80_2.jpg","sales":"336","rating":"5.0","rating_decimal":"4.90","cost":"37.00","uploaded_on":"Fri May 20 18:03:54 +1000 2011","last_update":"Fri May 20 18:03:54 +1000 2011","tags":"3d city, 3d street, billboards, buildings, business, commercial, corporate, led screens, multicolor, neon, new york, night city, shop, times square, town","category":"after-effects-project-files\/video-displays\/3d-object","live_preview_url":"https:\/\/0.s3.envato.com\/files\/65676464\/My%20New%20York%20video%20project%20template%20for%20after%20effects.jpg","live_preview_video_url":"https:\/\/0.s3.envato.com\/files\/2474432\/Preview_FLV.flv"}