{"id":"6492714","item":"Bike Wheel Intro\/Outro","url":"http:\/\/videohive.net\/item\/bike-wheel-introoutro\/6492714","user":"TeodrisAtlantis","thumbnail":"https:\/\/0.s3.envato.com\/files\/76959993\/Wheel80x80.png","sales":"11","rating":"0.0","rating_decimal":"0.00","cost":"20.00","uploaded_on":"Tue Dec 31 01:43:16 +1100 2013","last_update":"Tue Dec 31 01:43:16 +1100 2013","tags":"3d, bike, bmx, credits, end credits, film intro, film outro, intro, mountain bike, opener, outro, tire, titles, tony hawk, wheel","category":"after-effects-project-files\/openers\/3d-object","live_preview_url":"https:\/\/0.s3.envato.com\/files\/76960031\/wheel590x332.png","live_preview_video_url":"https:\/\/0.s3.envato.com\/files\/76960030\/finaltrailer.mp4"}