{"id":"6293802","item":"Search for Radio Stations","url":"http:\/\/videohive.net\/item\/search-for-radio-stations\/6293802","user":"Christian_Fletcher","thumbnail":"https:\/\/0.s3.envato.com\/files\/74668508\/Thumbnail.jpg","sales":"7","rating":"0.0","rating_decimal":"0.00","cost":"5.00","uploaded_on":"Thu Dec 05 09:54:35 +1100 2013","last_update":"Thu Dec 05 09:54:35 +1100 2013","tags":"am, antenna, broadcast, broadcasting, button, communication, find, fm, knob, listen, radio, search, speaker, tuner, waves","category":"stock-footage\/technology","live_preview_url":"https:\/\/0.s3.envato.com\/files\/74668514\/Preview.jpg","live_preview_video_url":"https:\/\/0.s3.envato.com\/files\/74668512\/Preview.mp4"}