{"id":"8246675","item":"Dozer Grader Working ","url":"http:\/\/videohive.net\/item\/dozer-grader-working-\/8246675","user":"eldelik","thumbnail":"https:\/\/0.s3.envato.com\/files\/97467405\/dozer-greyder-works_HDthumb-80x80.jpg","sales":"0","rating":"0.0","rating_decimal":"0.00","cost":"6.00","uploaded_on":"Thu Jul 17 01:31:49 +1000 2014","last_update":"Thu Jul 17 01:31:49 +1000 2014","tags":"build, bulldozer, construction, digging, dirt, dozer, equipment, grader, heavy, industrial, iron, machine, machinery, power, vehicle","category":"stock-footage\/education","live_preview_url":"https:\/\/0.s3.envato.com\/files\/97467408\/dozer-greyder-works_HDpreview-thumb.jpg","live_preview_video_url":"https:\/\/0.s3.envato.com\/files\/97467407\/dozer-greyder-works_HD.flv"}