{"id":"8099631","item":"Business Woman Writing - 2 Clips","url":"http:\/\/videohive.net\/item\/business-woman-writing-2-clips\/8099631","user":"crproductions","thumbnail":"https:\/\/0.s3.envato.com\/files\/95576889\/thumb.jpg","sales":"4","rating":"0.0","rating_decimal":"0.00","cost":"9.00","uploaded_on":"Sat Jun 28 04:38:53 +1000 2014","last_update":"Sat Jun 28 04:38:53 +1000 2014","tags":"boss, business, city, conference, corporate, job, office, professional, suit, table, woman, women, writing","category":"stock-footage\/business-corporate","live_preview_url":"https:\/\/0.s3.envato.com\/files\/95576892\/preview%20image.jpg","live_preview_video_url":"https:\/\/0.s3.envato.com\/files\/95576891\/preview%20video.mp4"}