{"id":"3217973","item":"Clouds HDR Wide 4K","url":"http:\/\/videohive.net\/item\/clouds-hdr-wide-4k\/3217973","user":"nyc_media_group","thumbnail":"https:\/\/3.s3.envato.com\/files\/37108969\/4k-wide-sky-hrd-80x80.jpg","sales":"1","rating":"0.0","rating_decimal":"0.00","cost":"30.00","uploaded_on":"Sat Oct 20 06:24:42 +1100 2012","last_update":"Sat Oct 20 06:24:42 +1100 2012","tags":"4k, blue, clouds, fast, hdr, motion, white","category":"stock-footage\/nature","live_preview_url":"https:\/\/2.s3.envato.com\/files\/37108972\/4k-wide-sky-hrd_pic.jpg","live_preview_video_url":"https:\/\/1.s3.envato.com\/files\/37672538\/4k-wide-sky-hrd_pre-2.flv"}