{"id":"1578286","item":"Vector Zoom","url":"http:\/\/videohive.net\/item\/vector-zoom\/1578286","user":"luckystars","thumbnail":"https:\/\/0.s3.envato.com\/files\/18204587\/vector%20zoom_thumb.jpg","sales":"1","rating":"0.0","rating_decimal":"0.00","cost":"6.00","uploaded_on":"Fri Feb 17 22:13:01 +1100 2012","last_update":"Fri Feb 17 22:13:01 +1100 2012","tags":"background, bg, broadcast, corporate, lines, shapes, tech, vector","category":"motion-graphics\/backgrounds\/abstract","live_preview_url":"https:\/\/0.s3.envato.com\/files\/18204588\/vector%20zoom590x300.jpg","live_preview_video_url":"https:\/\/0.s3.envato.com\/files\/18204589\/vector%20zoom.flv"}