{"id":"1070281","item":"Arc Background","url":"http:\/\/videohive.net\/item\/arc-background\/1070281","user":"digital_box","thumbnail":"https:\/\/0.s3.envato.com\/files\/12476262\/thumbnail.jpg","sales":"25","rating":"0.0","rating_decimal":"0.00","cost":"4.00","uploaded_on":"Fri Dec 16 15:47:59 +1100 2011","last_update":"Fri Dec 16 15:47:59 +1100 2011","tags":"3d, arc, background, blue, box, circle, design, digital, glass, loop, motion, scifi, sepia, tech, technology","category":"motion-graphics\/backgrounds\/abstract","live_preview_url":"https:\/\/1.s3.envato.com\/files\/12476260\/arcs-banner.jpg","live_preview_video_url":"https:\/\/0.s3.envato.com\/files\/12476263\/video_preview.flv"}