{"id":"7989576","item":"Business Woman Working At Cafe 2","url":"http:\/\/videohive.net\/item\/business-woman-working-at-cafe-2\/7989576","user":"eldelik","thumbnail":"https:\/\/0.s3.envato.com\/files\/94335707\/7W3C0794-commercial_THUMB-thumb-80x80.jpg","sales":"0","rating":"0.0","rating_decimal":"0.00","cost":"6.00","uploaded_on":"Wed Jun 18 01:26:09 +1000 2014","last_update":"Wed Jun 18 01:26:09 +1000 2014","tags":"business, cafe, cellphone, communication, computer, drink, freelance, hat, holiday, internet, job, laptop, leisure, talking, travel","category":"stock-footage\/people","live_preview_url":"https:\/\/0.s3.envato.com\/files\/94335755\/7W3C0794-commercial_THUMB_preview-thumb.jpg","live_preview_video_url":"https:\/\/0.s3.envato.com\/files\/94335754\/7W3C0794-commercial_HD.flv"}