{"id":"7640801","item":"Cute Cat","url":"http:\/\/videohive.net\/item\/cute-cat\/7640801","user":"EnginSezer","thumbnail":"https:\/\/0.s3.envato.com\/files\/90290948\/P4300252%20thumbnail.jpg","sales":"0","rating":"0.0","rating_decimal":"0.00","cost":"6.00","uploaded_on":"Tue May 06 08:33:20 +1000 2014","last_update":"Tue May 06 08:33:20 +1000 2014","tags":"beautiful, calm, cat, chair, cute, domestic cat, eyes, female, fur, home, indoor, sitting, watching, white, yellow","category":"stock-footage\/nature","live_preview_url":"https:\/\/0.s3.envato.com\/files\/90290951\/P4300252%20preview%20image.jpg","live_preview_video_url":"https:\/\/0.s3.envato.com\/files\/90290950\/P4300252%20video%20preview.mp4"}