{"id":"180557","item":"Disco lights loop","url":"http:\/\/videohive.net\/item\/disco-lights-loop\/180557","user":"unidos","thumbnail":"https:\/\/2.s3.envato.com\/files\/1765112\/disco-lights-thumb.jpg","sales":"52","rating":"5.0","rating_decimal":"5.00","cost":"3.00","uploaded_on":"Wed Mar 23 14:13:36 +1100 2011","last_update":"Wed Mar 23 14:13:36 +1100 2011","tags":"blue, club, disco, disco ball, green, laser, light, music, red, spike ball, strobe light, white, yellow","category":"motion-graphics\/elements\/light","live_preview_url":"https:\/\/2.s3.envato.com\/files\/1765111\/disco-lights-prev.jpg","live_preview_video_url":"https:\/\/1.s3.envato.com\/files\/1765113\/disco%20lights%20preview.flv"}