{"id":"157159","item":"Bar Graph 3D","url":"http:\/\/videohive.net\/item\/bar-graph-3d\/157159","user":"preussner","thumbnail":"https:\/\/2.s3.envato.com\/files\/1515008\/bar_graph_thumbnail.jpg","sales":"45","rating":"0.0","rating_decimal":"0.00","cost":"30.00","uploaded_on":"Thu Feb 03 09:09:39 +1100 2011","last_update":"Thu Feb 03 09:09:39 +1100 2011","tags":"annual report, bar, bar graph, black, blue, bussines, light blue, movement, orange, powerpoint, presentation, statistics, white","category":"cinema-4d-templates\/elements\/miscellaneous\/corporate","live_preview_url":"https:\/\/0.s3.envato.com\/files\/1515007\/bar_graph_vid_preview.jpg","live_preview_video_url":"https:\/\/2.s3.envato.com\/files\/1515009\/bar_graph_3d.flv"}