{"id":"6576276","item":"Flame Thrower","url":"http:\/\/videohive.net\/item\/flame-thrower\/6576276","user":"mFeher","thumbnail":"https:\/\/0.s3.envato.com\/files\/77902767\/Flamethrower%20thumbnail.jpg","sales":"23","rating":"0.0","rating_decimal":"0.00","cost":"6.00","uploaded_on":"Tue Jan 14 14:30:50 +1100 2014","last_update":"Tue Jan 14 14:30:50 +1100 2014","tags":"100 fps, fire, flame, flame thrower, slowmotion flame, vfx","category":"motion-graphics\/elements\/fire","live_preview_url":"https:\/\/0.s3.envato.com\/files\/77902774\/Flamethrower%20preview.jpg","live_preview_video_url":"https:\/\/0.s3.envato.com\/files\/77902773\/Presentation%20videohive%20flamethrower.mp4"}