{"id":"6844270","item":"Cinematic Video Camera","url":"http:\/\/videohive.net\/item\/cinematic-video-camera\/6844270","user":"zavarykin","thumbnail":"https:\/\/0.s3.envato.com\/files\/81071532\/CameraTurn%20(0-00-03-09)thumbnail.jpg","sales":"18","rating":"0.0","rating_decimal":"0.00","cost":"9.00","uploaded_on":"Tue Feb 18 02:42:42 +1100 2014","last_update":"Tue Feb 18 02:42:42 +1100 2014","tags":"advertisement, broadcasting, camera, cinema, company, filming, focusing, lens, news, production, professional, show-reel, tripod, tv, video","category":"stock-footage\/technology","live_preview_url":"https:\/\/0.s3.envato.com\/files\/81071537\/CameraTurn%20(0-00-03-09).jpg","live_preview_video_url":"https:\/\/0.s3.envato.com\/files\/81071536\/VideoCamera.mp4"}