{"id":"2793337","item":"The Sun","url":"http:\/\/videohive.net\/item\/the-sun\/2793337","user":"rover5","thumbnail":"https:\/\/0.s3.envato.com\/files\/32169495\/sunthumbnail.jpg","sales":"96","rating":"4.5","rating_decimal":"4.57","cost":"5.00","uploaded_on":"Wed Aug 08 04:37:18 +1000 2012","last_update":"Wed Aug 08 04:37:18 +1000 2012","tags":"evening, hands, male, man, natural, nature, people, silhouette, sky, spirit, spiritual, sun, sunlight, sunset","category":"stock-footage\/people","live_preview_url":"https:\/\/0.s3.envato.com\/files\/32169498\/sun590x300.jpg","live_preview_video_url":"https:\/\/0.s3.envato.com\/files\/32169497\/sunpreview.flv"}