{"id":"6853244","item":"Zed Slide Motion","url":"http:\/\/videohive.net\/item\/zed-slide-motion\/6853244","user":"Zedpromedia","thumbnail":"https:\/\/0.s3.envato.com\/files\/81151226\/SlideMotion_THUMB.jpg","sales":"46","rating":"0.0","rating_decimal":"0.00","cost":"27.00","uploaded_on":"Wed Feb 19 00:32:50 +1100 2014","last_update":"Wed Feb 19 00:32:50 +1100 2014","tags":"Apple Motion 5, birthday, display, emotional, fun, funeral, happy, intro, memories, showcase, slide show, special event, trip, vacation","category":"apple-motion-templates\/video-displays\/special-events","live_preview_url":"https:\/\/0.s3.envato.com\/files\/81151229\/SlideMotion_PREVIEW.jpg","live_preview_video_url":"https:\/\/0.s3.envato.com\/files\/81151228\/ZedSlideMotionPreview.mp4"}