{"id":"1406741","item":"Under The Water ","url":"http:\/\/videohive.net\/item\/under-the-water-\/1406741","user":"geroarias1987","thumbnail":"https:\/\/0.s3.envato.com\/files\/16269100\/thumball.jpg","sales":"61","rating":"4.0","rating_decimal":"4.00","cost":"10.00","uploaded_on":"Tue Jan 31 22:56:40 +1100 2012","last_update":"Tue Jan 31 22:56:40 +1100 2012","tags":"agua, aqua, aquatic, business, deep, fish, intro, logo, ocean, sea, soft, typography, under, water","category":"after-effects-project-files\/logo-stings\/water","live_preview_url":"https:\/\/0.s3.envato.com\/files\/16269103\/Under%20the%20water%20preview.jpg","live_preview_video_url":"https:\/\/0.s3.envato.com\/files\/16269101\/Under%20the%20water.flv"}