{"id":"1747634","item":"Happy Wedding V2","url":"http:\/\/videohive.net\/item\/happy-wedding-v2\/1747634","user":"usmanrafi","thumbnail":"https:\/\/3.s3.envato.com\/files\/62128763\/Happy%20Wedding%20V2.png","sales":"54","rating":"5.0","rating_decimal":"4.86","cost":"25.00","uploaded_on":"Wed Mar 07 04:20:35 +1100 2012","last_update":"Wed Mar 07 06:47:14 +1100 2012","tags":"3d, brown, dynamic, flares, fresh, glow, gold, light, movie, platinum, promo, ring, silver, stylish, wedding","category":"after-effects-project-files\/openers\/3d-object","live_preview_url":"https:\/\/2.s3.envato.com\/files\/20123740\/Happy%20Wedding%20V2_Preview%20Image.png","live_preview_video_url":"https:\/\/2.s3.envato.com\/files\/20391765\/Happy%20Wedding%20V2_Video%20Preview.flv"}