{"id":"3624390","item":"Cartoon Character Pack of Boy Girl and Dog","url":"http:\/\/videohive.net\/item\/cartoon-character-pack-of-boy-girl-and-dog\/3624390","user":"greatscottdesigns","thumbnail":"https:\/\/0.s3.envato.com\/files\/43459818\/cartoon-character-pack-dog-male-female-80x80.jpg","sales":"52","rating":"4.5","rating_decimal":"4.45","cost":"16.00","uploaded_on":"Sat Dec 15 08:06:28 +1100 2012","last_update":"Sat Dec 15 08:06:28 +1100 2012","tags":"boy, cartoon animation template, cartoon dog, girl","category":"after-effects-project-files\/openers\/cartoons","live_preview_url":"https:\/\/0.s3.envato.com\/files\/43459821\/cartoon-character-pack-dog-male-female-large.jpg","live_preview_video_url":"https:\/\/0.s3.envato.com\/files\/43459820\/cartoon-character-boy-girl-dog.flv"}