{"id":"8038250","item":"Disco Logo Opener","url":"http:\/\/videohive.net\/item\/disco-logo-opener\/8038250","user":"bessonica","thumbnail":"https:\/\/0.s3.envato.com\/files\/94853720\/Thumbnail_dlo.jpg","sales":"53","rating":"0.0","rating_decimal":"0.00","cost":"10.00","uploaded_on":"Fri Jun 20 20:44:58 +1000 2014","last_update":"Fri Jul 11 04:22:18 +1000 2014","tags":"bright, colorful, crazy, dance, disco, dubstep, electro, flat, geometry, intro, lines, purple, shapes, triangles, vector","category":"after-effects-project-files\/logo-stings\/electric","live_preview_url":"https:\/\/0.s3.envato.com\/files\/94853724\/preview_dlo.jpg","live_preview_video_url":"https:\/\/0.s3.envato.com\/files\/97164679\/preview_dlo_upd_sound.mp4"}