{"id":"1623819","item":"Cherries Close Up","url":"http:\/\/videohive.net\/item\/cherries-close-up\/1623819","user":"Ghoraa","thumbnail":"https:\/\/0.s3.envato.com\/files\/18714112\/Thumbnail%20(0.00.09.16).jpg","sales":"6","rating":"0.0","rating_decimal":"0.00","cost":"5.00","uploaded_on":"Sun Feb 26 08:14:08 +1100 2012","last_update":"Sun Feb 26 08:14:08 +1100 2012","tags":"berry, cherries, cherry, clip, close up, commercial, food, footage, fruit, organic, red, stock, supermarket, vegetable, video","category":"stock-footage\/food","live_preview_url":"https:\/\/1.s3.envato.com\/files\/18714115\/Preview%20(0.00.10.18).jpg","live_preview_video_url":"https:\/\/0.s3.envato.com\/files\/18714114\/FLV%20sample.flv"}