{"id":"6051295","item":"It's Xmas!","url":"http:\/\/videohive.net\/item\/its-xmas\/6051295","user":"steve314","thumbnail":"https:\/\/0.s3.envato.com\/files\/72018177\/Its%20Christmas%20plasticine%20ae%20bumper%20e-card%2080.jpg","sales":"7","rating":"0.0","rating_decimal":"0.00","cost":"20.00","uploaded_on":"Wed Nov 13 01:55:19 +1100 2013","last_update":"Wed Nov 13 01:55:19 +1100 2013","tags":"card, children, christmas, clay, deer, greetings, holidays, ident, kids, magical, merry christmas, motion card, wishes, x-mas, xmas","category":"after-effects-project-files\/openers\/holidays","live_preview_url":"https:\/\/0.s3.envato.com\/files\/72018181\/its%20Xmas%20-%20Holiday%20and%20New%20Years%20Eve%20greetings%20E-CARD.jpg","live_preview_video_url":"https:\/\/0.s3.envato.com\/files\/72018180\/ITS%20XMAS%20-holiday%20-seasons%20greetings%20e-card%20960.mp4"}