{"id":"3784317","item":"Valentine's Stop Motion","url":"http:\/\/videohive.net\/item\/valentines-stop-motion\/3784317","user":"SebicheArgentino","thumbnail":"https:\/\/3.s3.envato.com\/files\/45344949\/THM%20copy.jpg","sales":"95","rating":"4.5","rating_decimal":"4.67","cost":"15.00","uploaded_on":"Thu Jan 17 00:37:23 +1100 2013","last_update":"Thu Jan 17 00:37:23 +1100 2013","tags":"clean, couple, love, motion, red, stop, stop motion, valentine's, valentine's day, valentines","category":"apple-motion-templates\/openers\/special-events","live_preview_url":"https:\/\/3.s3.envato.com\/files\/45344953\/PREVIEW%20copy.jpg","live_preview_video_url":"https:\/\/3.s3.envato.com\/files\/45344952\/Comp%201.flv"}