{"id":"6103879","item":"Breaking Glass Logo","url":"http:\/\/videohive.net\/item\/breaking-glass-logo\/6103879","user":"D_Cooper","thumbnail":"https:\/\/0.s3.envato.com\/files\/72563933\/th.png","sales":"126","rating":"4.5","rating_decimal":"4.50","cost":"13.00","uploaded_on":"Sat Nov 16 12:13:04 +1100 2013","last_update":"Tue Nov 26 18:34:34 +1100 2013","tags":"breaker, crash, dark, debris, destroy, destruction, divide, explosion, ice, impact, lens, shatter, split, strike, strong","category":"after-effects-project-files\/logo-stings\/abstract","live_preview_url":"https:\/\/0.s3.envato.com\/files\/72563938\/preview.jpg","live_preview_video_url":"https:\/\/0.s3.envato.com\/files\/73144900\/BGLpreview.flv"}