{"id":"3173791","item":"Minimal World Globe","url":"http:\/\/videohive.net\/item\/minimal-world-globe\/3173791","user":"Mangustas","thumbnail":"https:\/\/0.s3.envato.com\/files\/36603091\/thumbnail.jpg","sales":"107","rating":"4.0","rating_decimal":"4.22","cost":"5.00","uploaded_on":"Wed Oct 10 14:14:40 +1100 2012","last_update":"Wed Oct 10 14:14:40 +1100 2012","tags":"cartoon, earth, global, globe, map, minimal, planet, space, sphere, style, stylish, world","category":"motion-graphics\/backgrounds\/space","live_preview_url":"https:\/\/0.s3.envato.com\/files\/36603102\/preview.jpg","live_preview_video_url":"https:\/\/0.s3.envato.com\/files\/36603101\/minimal%20world%20globe_preview.flv"}