{"id":"7564476","item":"Doctor Does Notes","url":"http:\/\/videohive.net\/item\/doctor-does-notes\/7564476","user":"Gorodenkoffs","thumbnail":"https:\/\/0.s3.envato.com\/files\/89453836\/Doctor_writing_thumbnail.jpg","sales":"2","rating":"0.0","rating_decimal":"0.00","cost":"30.00","uploaded_on":"Thu Apr 24 23:38:25 +1000 2014","last_update":"Thu Apr 24 23:38:25 +1000 2014","tags":"aid, doctor, help, invoice, male, mark, medical insurance, medicine, note, paperwork, pen, receipt, scientist, service, write","category":"stock-footage\/medical","live_preview_url":"https:\/\/0.s3.envato.com\/files\/89453912\/Doctor_writing_590.jpg","live_preview_video_url":"https:\/\/0.s3.envato.com\/files\/89453909\/Doctor_writing.mov.flv"}