{"id":"5800984","item":"Global News Ident Broadcast Pack","url":"http:\/\/videohive.net\/item\/global-news-ident-broadcast-pack\/5800984","user":"Pulsarus","thumbnail":"https:\/\/0.s3.envato.com\/files\/70057306\/thumb.jpg","sales":"9","rating":"0.0","rating_decimal":"0.00","cost":"32.00","uploaded_on":"Thu Oct 17 11:21:00 +1100 2013","last_update":"Thu Oct 17 11:21:00 +1100 2013","tags":"3d, broadcast, corporate, flares, glass, globe, ident, intro, media, news, opener, package, radio, tv, world","category":"cinema-4d-templates\/openers\/corporate","live_preview_url":"https:\/\/0.s3.envato.com\/files\/70057310\/global_news_broadcast_pack_cinema4d_template.jpg","live_preview_video_url":"https:\/\/0.s3.envato.com\/files\/70057309\/global_news_broadcast_pack_cinema4d_template_videohive.flv"}