{"id":"8193476","item":"Silhouette Woman Play Guitar","url":"http:\/\/videohive.net\/item\/silhouette-woman-play-guitar\/8193476","user":"nyc_media_group","thumbnail":"https:\/\/0.s3.envato.com\/files\/96781546\/silhouette-woman-play-guitar-80x80.jpg","sales":"0","rating":"0.0","rating_decimal":"0.00","cost":"7.00","uploaded_on":"Sat Jul 12 08:31:23 +1000 2014","last_update":"Sat Jul 12 08:31:23 +1000 2014","tags":"acoustic, artist, girl, guitar, holding, instrument, musical, musician, performing, person, play, shadow, shape, silhouette, woman","category":"stock-footage\/slow-motion","live_preview_url":"https:\/\/0.s3.envato.com\/files\/96781567\/silhouette-woman-play-guitar-pic.jpg","live_preview_video_url":"https:\/\/0.s3.envato.com\/files\/96781564\/silhouette-woman-play-guitar-preview-l.flv"}