{"id":"4547893","item":"Good Promo","url":"http:\/\/videohive.net\/item\/good-promo\/4547893","user":"motionsv","thumbnail":"https:\/\/1.s3.envato.com\/files\/54236332\/80x80.jpg","sales":"17","rating":"0.0","rating_decimal":"0.00","cost":"20.00","uploaded_on":"Tue Apr 23 10:26:17 +1000 2013","last_update":"Tue Apr 23 10:26:17 +1000 2013","tags":"advertising, animation, business, circles, clean, commercial, company, corporate, dynamic, portfolio, presentation, profile, promo, typography, web video","category":"after-effects-project-files\/openers\/corporate","live_preview_url":"https:\/\/3.s3.envato.com\/files\/54236335\/590x300.jpg","live_preview_video_url":"https:\/\/0.s3.envato.com\/files\/54236334\/preview.flv"}