{"id":"241352","item":"Shark","url":"http:\/\/videohive.net\/item\/shark\/241352","user":"spc01","thumbnail":"https:\/\/2.s3.envato.com\/files\/2466649\/80x80_HDV_010_shark_2.jpg","sales":"38","rating":"4.5","rating_decimal":"4.40","cost":"6.00","uploaded_on":"Mon May 16 14:08:03 +1000 2011","last_update":"Mon May 16 14:08:03 +1000 2011","tags":"aquarium, blue, danger, deadly, deep, fish, life, marine, ocean, reef, sea, shark, swimming, teeth, underwater","category":"stock-footage\/nature","live_preview_url":"https:\/\/1.s3.envato.com\/files\/2463738\/HDV_010_shark.jpg","live_preview_video_url":"https:\/\/1.s3.envato.com\/files\/2463740\/HDV_010_shark.flv"}