{"id":"2806932","item":"Dancing Silhouettes","url":"http:\/\/videohive.net\/item\/dancing-silhouettes\/2806932","user":"Pressmaster","thumbnail":"https:\/\/0.s3.envato.com\/files\/32359848\/MVI_5889-26_2.jpg","sales":"27","rating":"0.0","rating_decimal":"0.00","cost":"6.00","uploaded_on":"Mon Aug 13 03:26:43 +1000 2012","last_update":"Mon Aug 13 03:26:43 +1000 2012","tags":"dancing, dynamic, evening, excitement, female, friendship, fun, happiness, lifestyle, male, party, people, resort, shadow, silhouette","category":"stock-footage\/lifestyle","live_preview_url":"https:\/\/0.s3.envato.com\/files\/32359851\/MVI_5889-26.jpg","live_preview_video_url":"https:\/\/0.s3.envato.com\/files\/32359850\/MVI_5889-26.flv"}