{"id":"6072036","item":"Relationship Victory","url":"http:\/\/videohive.net\/item\/relationship-victory\/6072036","user":"XnitroX","thumbnail":"https:\/\/0.s3.envato.com\/files\/72237299\/Relationship_Victory_240fps_80x80.jpg","sales":"14","rating":"0.0","rating_decimal":"0.00","cost":"13.00","uploaded_on":"Thu Nov 14 07:34:29 +1100 2013","last_update":"Thu Nov 14 07:34:29 +1100 2013","tags":"celebrate, couple, engagement, happiness, holding hands, jumping, love, romance, silhouette, slow motion, success, sunset, togetherness, winning","category":"stock-footage\/people","live_preview_url":"https:\/\/0.s3.envato.com\/files\/72237306\/Relationship_Victory_240fps_590x300.jpg","live_preview_video_url":"https:\/\/0.s3.envato.com\/files\/72835817\/Relationship_Victory_960x540.flv"}