{"id":"2536452","item":"Bobby Promotes","url":"http:\/\/videohive.net\/item\/bobby-promotes\/2536452","user":"flasheasy","thumbnail":"https:\/\/0.s3.envato.com\/files\/105380635\/BobbyPromotes_Thumbnail.jpg","sales":"799","rating":"5.0","rating_decimal":"4.86","cost":"37.00","uploaded_on":"Thu Jun 21 22:00:23 +1000 2012","last_update":"Fri Sep 19 00:03:10 +1000 2014","tags":"3d, animation, cartoon, character, clean, funny, man, marketing, original, portfolio, presentation, product, promo, promote, service","category":"after-effects-project-files\/openers\/corporate","live_preview_url":"https:\/\/0.s3.envato.com\/files\/105380645\/BobbyPromotes_Preview_Image.jpg","live_preview_video_url":"https:\/\/0.s3.envato.com\/files\/105380644\/Bobby_Promotes_640x360.mp4"}