{"id":"316139","item":"Sunset Timelapse Berlin Reichstag","url":"http:\/\/videohive.net\/item\/sunset-timelapse-berlin-reichstag\/316139","user":"kuhlmotion","thumbnail":"https:\/\/0.s3.envato.com\/files\/3629443\/Reichstag_Sunset.jpg","sales":"60","rating":"4.5","rating_decimal":"4.67","cost":"6.00","uploaded_on":"Fri Jul 01 22:56:00 +1000 2011","last_update":"Fri Jul 01 22:56:00 +1000 2011","tags":"berlin, bundestag, city, deutsch, europe, germany, news, parliament, reichstag, reichstag building, sunset, time lapse","category":"stock-footage\/time-lapse","live_preview_url":"https:\/\/0.s3.envato.com\/files\/3538711\/110629_Reichstag_Sunset_3-1.jpeg","live_preview_video_url":"https:\/\/0.s3.envato.com\/files\/3629444\/Reichstag_Sunset.flv"}