{"id":"3584396","item":"Red Sparkle Fashion Project","url":"http:\/\/videohive.net\/item\/red-sparkle-fashion-project\/3584396","user":"brownale9000","thumbnail":"https:\/\/0.s3.envato.com\/files\/42962433\/Red%20Sparkle%2080x80.jpg","sales":"29","rating":"5.0","rating_decimal":"5.00","cost":"21.00","uploaded_on":"Tue Dec 11 21:55:41 +1100 2012","last_update":"Tue Dec 11 21:55:41 +1100 2012","tags":"diamonds, elegant, fashion, glamor, glitter, intro, lights, particles, red, retro, simple, sparkle, transition, video display, video transition","category":"after-effects-project-files\/video-displays\/miscellaneous","live_preview_url":"https:\/\/0.s3.envato.com\/files\/42962436\/Red%20Sparkle%20Still%20Large%2001.jpg","live_preview_video_url":"https:\/\/0.s3.envato.com\/files\/42962435\/Red%20Sparkle%20FLV.flv"}