{"id":"7288199","item":"Bokeh And Golden Lights","url":"http:\/\/videohive.net\/item\/bokeh-and-golden-lights\/7288199","user":"sfxstudio","thumbnail":"https:\/\/1.s3.envato.com\/files\/86252779\/BokehAndGoldenLights_Thumbnail.jpg","sales":"14","rating":"0.0","rating_decimal":"0.00","cost":"25.00","uploaded_on":"Tue Apr 01 01:07:51 +1100 2014","last_update":"Tue Apr 01 01:07:51 +1100 2014","tags":"bokeh, cinematic, elegant, fashion, film, flare, focus, glossy, gold, light, memories, opener, peoples, shiny, slideshow","category":"after-effects-project-files\/video-displays\/light","live_preview_url":"https:\/\/2.s3.envato.com\/files\/86252792\/BokehAndGoldenLights_Preview-Image.jpg","live_preview_video_url":"https:\/\/1.s3.envato.com\/files\/86252789\/BokehAndGoldenLights_Video-Preview.flv"}