{"id":"4514297","item":"Yellowed Book Thrown To Dumpster ","url":"http:\/\/videohive.net\/item\/yellowed-book-thrown-to-dumpster-\/4514297","user":"Christian_Fletcher","thumbnail":"https:\/\/2.s3.envato.com\/files\/53842959\/Thumbnail.jpg","sales":"1","rating":"0.0","rating_decimal":"0.00","cost":"5.00","uploaded_on":"Thu Apr 18 11:34:47 +1000 2013","last_update":"Thu Apr 18 11:34:47 +1000 2013","tags":"book, civility, education, garbage, learning, lecture, misery, pages, pale, reading, rubbish, school, schooling, trash, yellowed","category":"stock-footage\/education","live_preview_url":"https:\/\/1.s3.envato.com\/files\/53842963\/Preview.jpg","live_preview_video_url":"https:\/\/2.s3.envato.com\/files\/53842962\/Preview.flv"}