{"id":"4570785","item":"Sweets Falling, Slow Motion, Filmed at 300FPS","url":"http:\/\/videohive.net\/item\/sweets-falling-slow-motion-filmed-at-300fps\/4570785","user":"alexbeck","thumbnail":"https:\/\/0.s3.envato.com\/files\/54484424\/sweets_TH.jpg","sales":"3","rating":"0.0","rating_decimal":"0.00","cost":"21.00","uploaded_on":"Thu Apr 25 23:35:22 +1000 2013","last_update":"Thu Apr 25 23:35:22 +1000 2013","tags":"Chocolate Drops, bouncing, candy, chocolate, color, colorful, colour, colourful, drops, falling, motion, reflecting, slow, slow motion, sweets","category":"stock-footage\/slow-motion","live_preview_url":"https:\/\/0.s3.envato.com\/files\/54484427\/sweets.jpg","live_preview_video_url":"https:\/\/0.s3.envato.com\/files\/54484426\/sweets.flv"}