{"id":"205667","item":"Packshot Backgrounds Collection","url":"http:\/\/videohive.net\/item\/packshot-backgrounds-collection\/205667","user":"steve314","thumbnail":"https:\/\/0.s3.envato.com\/files\/2012443\/packshot%2080.jpg","sales":"251","rating":"4.5","rating_decimal":"4.62","cost":"10.00","uploaded_on":"Thu Mar 31 01:08:14 +1100 2011","last_update":"Thu Mar 31 01:08:14 +1100 2011","tags":"ad, background, backgrounds, blue, bright, commercial, dark, light, pack, product, purple, red, soft, tech, tv","category":"after-effects-project-files\/elements\/backgrounds\/corporate","live_preview_url":"https:\/\/0.s3.envato.com\/files\/2012441\/packshot%20backgrounds%20590.jpg","live_preview_video_url":"https:\/\/0.s3.envato.com\/files\/2012444\/packshot%20collection%20640.flv"}