{"id":"2870674","item":"Traffic On Bridge At Night (Timelapse)","url":"http:\/\/videohive.net\/item\/traffic-on-bridge-at-night-timelapse\/2870674","user":"urbazon","thumbnail":"https:\/\/0.s3.envato.com\/files\/33019461\/Traffic%20on%20Bridge%20at%20Night%20thumb.jpg","sales":"1","rating":"0.0","rating_decimal":"0.00","cost":"6.00","uploaded_on":"Wed Aug 22 13:46:25 +1000 2012","last_update":"Wed Aug 22 13:46:25 +1000 2012","tags":"bridge, cars, city, dark, evening, lights, night, nighttime, people, time lapse, timelapse, traffic, vehicles","category":"stock-footage\/city","live_preview_url":"https:\/\/0.s3.envato.com\/files\/33019464\/Traffic%20on%20Bridge%20at%20Night%20preview%20image.jpg","live_preview_video_url":"https:\/\/0.s3.envato.com\/files\/33019463\/Traffic%20on%20Bridge%20at%20Night%20preview.flv"}