{"id":"3296238","item":"Flock of Birds","url":"http:\/\/videohive.net\/item\/flock-of-birds\/3296238","user":"doodool","thumbnail":"https:\/\/1.s3.envato.com\/files\/38405934\/Flock%20of%20birds%203%20smalll.jpg","sales":"14","rating":"0.0","rating_decimal":"0.00","cost":"5.00","uploaded_on":"Mon Oct 29 07:36:40 +1100 2012","last_update":"Mon Oct 29 07:36:40 +1100 2012","tags":"Ravens, air, animal, bird, black, blackbird, cloud, colony, crows, fauna, feather, flock, fly, nature, ornithology","category":"stock-footage\/nature","live_preview_url":"https:\/\/2.s3.envato.com\/files\/38405938\/Flock%20of%20birds%203.jpg","live_preview_video_url":"https:\/\/0.s3.envato.com\/files\/38405937\/Flock%20of%20birds%203.flv"}