{"id":"6270326","item":"Led Screen Count Down","url":"http:\/\/videohive.net\/item\/led-screen-count-down\/6270326","user":"template-fx","thumbnail":"https:\/\/1.s3.envato.com\/files\/74436923\/LedScreen_80x80.jpg","sales":"17","rating":"0.0","rating_decimal":"0.00","cost":"4.00","uploaded_on":"Sun Dec 01 08:41:00 +1100 2013","last_update":"Sun Dec 01 08:41:00 +1100 2013","tags":"count down, countdown, counting, fashion, led screen, lights, new year, spin, stars, timer, video","category":"motion-graphics\/backgrounds","live_preview_url":"https:\/\/3.s3.envato.com\/files\/74436979\/LedScreen_590x300.jpg","live_preview_video_url":"https:\/\/1.s3.envato.com\/files\/74436978\/LedCountdownPreview_960x540.flv"}