{"id":"8434047","item":"Sprinkle Powder Sugar on Strawberries","url":"http:\/\/videohive.net\/item\/sprinkle-powder-sugar-on-strawberries\/8434047","user":"Gorodenkoffs","thumbnail":"https:\/\/0.s3.envato.com\/files\/99641429\/Sprinkle_powder_sugar_on_srawberries_T.jpg","sales":"0","rating":"0.0","rating_decimal":"0.00","cost":"30.00","uploaded_on":"Tue Aug 05 04:20:27 +1000 2014","last_update":"Tue Aug 05 04:20:27 +1000 2014","tags":"berry, dessert, eating, freshness, fruit, health, organic, powder, raw, red, sprinkle, strawberry, sugar, sweet, wash","category":"stock-footage\/food","live_preview_url":"https:\/\/0.s3.envato.com\/files\/99641542\/Sprinkle_powder_sugar_on_srawberries.jpg","live_preview_video_url":"https:\/\/0.s3.envato.com\/files\/99641540\/Sprinkle_powder_sugar_on_srawberries_1.flv"}