{"id":"7815293","item":"20 Digital Glitch Transitions","url":"http:\/\/videohive.net\/item\/20-digital-glitch-transitions\/7815293","user":"starfaII","thumbnail":"https:\/\/0.s3.envato.com\/files\/92286608\/thumb%20glitch.jpg","sales":"22","rating":"0.0","rating_decimal":"0.00","cost":"17.00","uploaded_on":"Wed May 28 08:02:38 +1000 2014","last_update":"Wed May 28 08:02:38 +1000 2014","tags":"digital, distortion, edit, error, fast, flare, flash, glitch, glow, lens blur, light, sci-fi, technology, transition, video","category":"motion-graphics\/transitions\/technology","live_preview_url":"https:\/\/0.s3.envato.com\/files\/92286657\/Preview%20image.jpg","live_preview_video_url":"https:\/\/0.s3.envato.com\/files\/92286654\/Preview%20video%20glitches.flv"}