{"id":"7749895","item":"Bronze Soldier Left Side View CU","url":"http:\/\/videohive.net\/item\/bronze-soldier-left-side-view-cu\/7749895","user":"Vintervarg","thumbnail":"https:\/\/0.s3.envato.com\/files\/91500112\/phpcO9zp5_c3AM.jpg","sales":"0","rating":"0.0","rating_decimal":"0.00","cost":"7.00","uploaded_on":"Sat May 17 03:45:58 +1000 2014","last_update":"Sat May 17 03:45:58 +1000 2014","tags":"army, award, celebration, courage, freedom, heroes, honor, insignia, nation, patriotism, pride, sculpture, victory, war, winning","category":"stock-footage\/military","live_preview_url":"https:\/\/0.s3.envato.com\/files\/91500145\/Bronze.Soldier.Left.Side.View.CU.jpg","live_preview_video_url":"https:\/\/0.s3.envato.com\/files\/91500144\/Sequence%201%20flv%20h264.flv"}