{"id":"111875","item":"Fire Stroke Logo","url":"http:\/\/videohive.net\/item\/fire-stroke-logo\/111875","user":"d3luxxxe","thumbnail":"https:\/\/1.s3.envato.com\/files\/1482143\/FireStroke%20-%20thumb.png","sales":"99","rating":"4.5","rating_decimal":"4.40","cost":"15.00","uploaded_on":"Thu Jul 08 22:17:44 +1000 2010","last_update":"Tue Jan 18 02:07:59 +1100 2011","tags":"3d, blue, closer, corporate, fire, identity, intro, logo, opener, orange","category":"after-effects-project-files\/openers\/fire","live_preview_url":"https:\/\/2.s3.envato.com\/files\/1482142\/Fire%20Stroke%20-%20preview.jpg","live_preview_video_url":"https:\/\/3.s3.envato.com\/files\/365298\/preview.flv"}