{"id":"5862582","item":"Skyscraper Day to Night","url":"http:\/\/videohive.net\/item\/skyscraper-day-to-night\/5862582","user":"Rickyloca","thumbnail":"https:\/\/0.s3.envato.com\/files\/69899863\/Skyscraper%20Day%20to%20Night%20thumbnail.jpg","sales":"22","rating":"0.0","rating_decimal":"0.00","cost":"6.00","uploaded_on":"Fri Oct 18 15:43:06 +1100 2013","last_update":"Fri Oct 18 15:43:06 +1100 2013","tags":"architecture, business, city, clouds, corporate, day, development, lifestyle, light, modern, night, people, storm, timelapse, urban","category":"stock-footage\/city","live_preview_url":"https:\/\/0.s3.envato.com\/files\/69899888\/Skyscraper%20Day%20to%20Night%20preview.jpg","live_preview_video_url":"https:\/\/0.s3.envato.com\/files\/69899886\/Skyscraper%20Day%20to%20Night.flv"}