{"id":"4240139","item":"Brown Lump Cane Sugar, Sliding Video (3-Pack)","url":"http:\/\/videohive.net\/item\/brown-lump-cane-sugar-sliding-video-3pack\/4240139","user":"HamsterMan","thumbnail":"https:\/\/0.s3.envato.com\/files\/50680986\/brown-lump-cane-sugar-sliding-turbinado_t.jpg","sales":"0","rating":"0.0","rating_decimal":"0.00","cost":"13.00","uploaded_on":"Sat Mar 16 00:35:05 +1100 2013","last_update":"Sat Mar 16 00:35:05 +1100 2013","tags":"Lump sugar, Sugarcane, brown, cane sugar, cane-sugar, chipped, food, granulated, ingredient, macro, molasses, panning, sliding, turbinado, unrefined","category":"stock-footage\/food","live_preview_url":"https:\/\/0.s3.envato.com\/files\/50681079\/brown-lump-cane-sugar-sliding-turbinado_p.jpg","live_preview_video_url":"https:\/\/0.s3.envato.com\/files\/50681076\/brown-lump-cane-sugar-sliding-turbinado.flv"}