{"id":"7989273","item":"Sexy Dancer On Waterfall In Borneo","url":"http:\/\/videohive.net\/item\/sexy-dancer-on-waterfall-in-borneo\/7989273","user":"eldelik","thumbnail":"https:\/\/0.s3.envato.com\/files\/94324988\/7W3C0635-part1-commercial_THUMB-thumb-80x80.jpg","sales":"0","rating":"0.0","rating_decimal":"0.00","cost":"5.00","uploaded_on":"Tue Jun 17 23:23:14 +1000 2014","last_update":"Tue Jun 17 23:23:14 +1000 2014","tags":"bikini, borneo, dancer, dancing, exotic, forest, jungle, malaysia, nature, rain, rainforest, tropical, water, waterfall, woman","category":"stock-footage\/nature","live_preview_url":"https:\/\/0.s3.envato.com\/files\/94325059\/7W3C0635-part1-commercial_THUMB_preview-thumb.jpg","live_preview_video_url":"https:\/\/0.s3.envato.com\/files\/94325058\/7W3C0635-part1-commercial_HD.flv"}