{"id":"4850785","item":"Corporate Layer Logo & Transition","url":"http:\/\/videohive.net\/item\/corporate-layer-logo-transition\/4850785","user":"Creattive","thumbnail":"https:\/\/0.s3.envato.com\/files\/57806255\/thumb.png","sales":"85","rating":"5.0","rating_decimal":"4.83","cost":"13.00","uploaded_on":"Thu Jun 06 20:30:44 +1000 2013","last_update":"Thu Jun 06 20:30:44 +1000 2013","tags":"bright, clean, company, corporate, layer, minimal, serious, simple, through, transition, travel, zoom","category":"after-effects-project-files\/logo-stings\/corporate","live_preview_url":"https:\/\/0.s3.envato.com\/files\/57806260\/previewjpeg.jpg","live_preview_video_url":"https:\/\/0.s3.envato.com\/files\/57806259\/corporatelayerlogo.flv"}