{"id":"4508597","item":"Through Glass Logo","url":"http:\/\/videohive.net\/item\/through-glass-logo\/4508597","user":"Wynio","thumbnail":"https:\/\/3.s3.envato.com\/files\/53772484\/thumb_glass.jpg","sales":"22","rating":"5.0","rating_decimal":"4.75","cost":"12.00","uploaded_on":"Wed Apr 17 17:22:19 +1000 2013","last_update":"Wed Apr 17 17:22:19 +1000 2013","tags":"bullet, dark, destroy, glass, glow, hit, impact, intro, logo, refraction, sharpnel, shatter, smash, sting, through","category":"after-effects-project-files\/logo-stings\/grunge","live_preview_url":"https:\/\/3.s3.envato.com\/files\/53772493\/preview_glass.jpg","live_preview_video_url":"https:\/\/2.s3.envato.com\/files\/53772492\/Through_glass_flash.flv"}