{"id":"6546964","item":"Stop Motion Nuts","url":"http:\/\/videohive.net\/item\/stop-motion-nuts\/6546964","user":"levmotion","thumbnail":"https:\/\/2.s3.envato.com\/files\/77636299\/TUMB.png","sales":"0","rating":"0.0","rating_decimal":"0.00","cost":"15.00","uploaded_on":"Fri Jan 10 15:35:45 +1100 2014","last_update":"Fri Jan 10 15:35:45 +1100 2014","tags":"colors, flares, form, nuts, opacity, pixel motion, shapes, stop motion, trapcode","category":"after-effects-project-files\/titles\/nature","live_preview_url":"https:\/\/1.s3.envato.com\/files\/77636310\/Preview.jpg","live_preview_video_url":"https:\/\/1.s3.envato.com\/files\/77636309\/preview.flv"}